mcp_agent_cloud/__init__.py
mcp_agent_cloud/_base_client.py
mcp_agent_cloud/_client.py
mcp_agent_cloud/_compat.py
mcp_agent_cloud/_constants.py
mcp_agent_cloud/_exceptions.py
mcp_agent_cloud/_files.py
mcp_agent_cloud/_models.py
mcp_agent_cloud/_qs.py
mcp_agent_cloud/_resource.py
mcp_agent_cloud/_response.py
mcp_agent_cloud/_streaming.py
mcp_agent_cloud/_types.py
mcp_agent_cloud/_version.py
mcp_agent_cloud/py.typed
mcp_agent_cloud/_utils/__init__.py
mcp_agent_cloud/_utils/_logs.py
mcp_agent_cloud/_utils/_proxy.py
mcp_agent_cloud/_utils/_reflection.py
mcp_agent_cloud/_utils/_streams.py
mcp_agent_cloud/_utils/_sync.py
mcp_agent_cloud/_utils/_transform.py
mcp_agent_cloud/_utils/_typing.py
mcp_agent_cloud/_utils/_utils.py
mcp_agent_cloud/lib/.keep
mcp_agent_cloud/resources/__init__.py
mcp_agent_cloud/resources/workflow.py
mcp_agent_cloud/types/__init__.py
mcp_agent_cloud/types/workflow_create_config_params.py
mcp_agent_cloud/types/workflow_create_config_response.py
mcp_agent_cloud/types/workflow_delete_config_params.py
mcp_agent_cloud/types/workflow_delete_config_response.py
mcp_agent_cloud/types/workflow_get_config_params.py
mcp_agent_cloud/types/workflow_get_config_response.py
mcp_agent_cloud/types/workflow_list_configs_params.py
mcp_agent_cloud/types/workflow_list_configs_response.py
mcp_agent_cloud/types/workflow_list_runs_params.py
mcp_agent_cloud/types/workflow_list_runs_response.py
mcp_agent_cloud/types/workflow_start_run_params.py
mcp_agent_cloud/types/workflow_start_run_response.py
mcp_agent_cloud/types/workflow_stop_run_params.py
mcp_agent_cloud/types/workflow_stop_run_response.py
mcp_agent_cloud-0.1.0a2.dist-info/METADATA
mcp_agent_cloud-0.1.0a2.dist-info/WHEEL
mcp_agent_cloud-0.1.0a2.dist-info/licenses/LICENSE
mcp_agent_cloud-0.1.0a2.dist-info/RECORD
